{
  "ff-story": {
    "name": "Story",
    "version": "v0.13.19",
    "commits": [
      {
        "sha": "e6ad4de",
        "message": "reorganize chapter files. add chapter prompts",
        "date": "2026-01-18T11:52:08.000Z",
        "url": "https://github.com/clevertree/ff-story/commit/e6ad4de"
      },
      {
        "sha": "9434393",
        "message": "feat(story): sync all 13+ chapter drafts and update manuscript",
        "date": "2026-01-17T19:02:49.000Z",
        "url": "https://github.com/clevertree/ff-story/commit/9434393"
      },
      {
        "sha": "bad70f4",
        "message": "docs: sync recent chapter and world-building changes",
        "date": "2026-01-17T18:51:46.000Z",
        "url": "https://github.com/clevertree/ff-story/commit/bad70f4"
      }
    ],
    "repoUrl": "https://github.com/clevertree/ff-story/commits/main/"
  },
  "ff-teaser": {
    "name": "Teaser",
    "version": "v0.9.9",
    "commits": [
      {
        "sha": "19f4a69",
        "message": "chore: update version and commit history",
        "date": "2026-01-16T13:33:32.000Z",
        "url": "https://github.com/clevertree/ff-teaser/commit/19f4a69"
      },
      {
        "sha": "99672b0",
        "message": "chore: sync metadata with 32-chapter structure",
        "date": "2026-01-14T17:38:10.000Z",
        "url": "https://github.com/clevertree/ff-teaser/commit/99672b0"
      },
      {
        "sha": "bc5785a",
        "message": "chore: sync metadata with 32-chapter structure",
        "date": "2026-01-14T16:04:16.000Z",
        "url": "https://github.com/clevertree/ff-teaser/commit/bc5785a"
      }
    ],
    "repoUrl": "https://github.com/clevertree/ff-teaser/commits/main/"
  },
  "forgotten-future-site": {
    "name": "Site",
    "version": "v0.11.17",
    "commits": [
      {
        "sha": "4cfbdbb",
        "message": "fix: resolve Cypress component test failures",
        "date": "2026-01-18T12:27:41.000Z",
        "url": "https://github.com/clevertree/forgotten-future-site/commit/4cfbdbb"
      },
      {
        "sha": "d20e3f0",
        "message": "chore: disable image optimization for static export (NEXT_PUBLIC_IS_STATIC)",
        "date": "2026-01-18T00:58:59.000Z",
        "url": "https://github.com/clevertree/forgotten-future-site/commit/d20e3f0"
      },
      {
        "sha": "8d25554",
        "message": "chore: sync COMMIT_HISTORY.md",
        "date": "2026-01-18T00:57:24.000Z",
        "url": "https://github.com/clevertree/forgotten-future-site/commit/8d25554"
      }
    ],
    "repoUrl": "https://github.com/clevertree/forgotten-future-site/commits/master/"
  }
}